[
  {
    "name": "Cnn_Turk",
    "url": "https://ytb.metvmetv83.workers.dev/?ID=UCV6zcRug6Hqp1UX_FdyUeBg"
  },
  {
    "name": "Haber_Turk",
    "url": "https://ytb.metvmetv83.workers.dev/?ID=UCn6dNfiRE_Xunu7iMyvD7AA"
  },
  {
    "name": "NTV",
    "url": "https://ytb.metvmetv83.workers.dev/?ID=UC9TDTjbOjFB9jADmPhSAPsw"
  },
  {
    "name": "Haber_Global_TV",
    "url": "https://ytb.metvmetv83.workers.dev/?ID=UCtc-a9ZUIg0_5HpsPxEO7Qg"
  },
    {
    "name": "A_haber",
    "url": "https://ytb.metvmetv83.workers.dev/?ID=UCKQhfw-lzz0uKnE1fY1PsAA"
  },
    {
    "name": "TRT_Haber",
    "url": "https://www.youtube.com/youtube/channel/UCBgTP2LOFVPmq15W-RH-WXA"
  },
    {
    "name": "Ekol_Tv",
    "url": "https://www.youtube.com/youtube/channel/UCccxXUKSuqOrlWQxweZBAQw"
  },
    {
    "name": "CNBC_E",
    "url": "https://ytb.metvmetv83.workers.dev/?ID=UCaO-M1dXacMwtyg0Pvovk4w"
  },
     {
    "name": "Halk_Tv",
    "url": "https://ytb.metvmetv83.workers.dev/?ID=UCf_ResXZzE-o18zACUEmyvQ"
  },
    {
    "name": "Sozcu_Tv",
    "url": "https://ytb.metvmetv83.workers.dev/?ID=UCOulx_rep5O4i9y6AyDqVvw"
  },
    {
    "name": "ShowMax",
    "url": "https://ytb.metvmetv83.workers.dev/?ID=UC9JMe_We017gYrRc7kZHgmg"
  },
      {
    "name": "24_Tv",
    "url": "https://ytb.metvmetv83.workers.dev/?ID=UCN7VYCsI4Lx1-J4_BtjoWUA"
  },
    {
    "name": "Ulke_Tv",
    "url": "https://ytb.metvmetv83.workers.dev/?ID=UCi65FGbYYj-OzJm2luB_fNQ"
  },
      {
    "name": "Flash_Haber",
    "url": "https://ytb.metvmetv83.workers.dev/?ID=UCNcjCb2RnA3eMMhTZSxZu3A"
  },
    {
    "name": "Benguturk_Tv",
    "url": "https://ytb.metvmetv83.workers.dev/?ID=UChNgvcVZ_ggDdZ0zCcuuzFw"
  },
    {
    "name": "Krt_Tv",
    "url": "https://ytb.metvmetv83.workers.dev/?ID=UCVKWwHoLwUMMa80cu_1uapA"
  },
    {
    "name": "Akit_Tv",
    "url": "https://ytb.metvmetv83.workers.dev/?ID=UCbaLyHJp6S9Lsj6oT9aJsQw"
  },
    {
    "name": "Tele_1",
    "url": "https://ytb.metvmetv83.workers.dev/?ID=UCoHnRpOS5rL62jTmSDO5Npw"
  },
    {
    "name": "Ulusal_Kanal",
    "url": "https://ytb.metvmetv83.workers.dev/?ID=UC6T0L26KS1NHMPbTwI1L4Eg"
  },
    {
    "name": "Tv_Net",
    "url": "https://ytb.metvmetv83.workers.dev/?ID=UC8rh34IlJTN0lDZlTwzWzjg"
  },
    {
    "name": "A_Spor",
    "url": "https://ytb.metvmetv83.workers.dev/?ID=UCJElRTCNEmLemgirqvsW63Q"
  },
    {
    "name": "Ht_Spor",
    "url": "https://ytb.metvmetv83.workers.dev/?ID=UCK3mI2lsk3LSo8PBUc8JTSw"
  },
    {
    "name": "Bein_Spor_Haber",
    "url": "https://ytb.metvmetv83.workers.dev/?ID=UCPe9vNjHF1kEExT5kHwc7aw"
  },
    {
    "name": "Bloomberg_Ht",
    "url": "https://ytb.metvmetv83.workers.dev/?ID=UCApLxl6oYQafxvykuoC2uxQ"
  },
      {
    "name": "Yesilcam_Arzufilm",
    "url": "https://ytb.metvmetv83.workers.dev/?ID=UCUALYmnkEmx8vlxIbpr2gmw"
  },
      {
    "name": "Kemal_SunalG",
    "url": "https://ytb.metvmetv83.workers.dev/?ID=UCHumSHRFQ8skiHTY75sxytQ"
  },
      {
    "name": "Kemal_SunalF",
    "url": "https://ytb.metvmetv83.workers.dev/?ID=UCoIUysIrvGxoDw-GkdOGjRw"
  },
      {
    "name": "Tgrt_Belgese",
    "url": "https://ytb.metvmetv83.workers.dev/?ID=UCkQV7uH1Otv47CZz6tD3jGQ"
  },
    {
    "name": "Eko_Turk",
    "url": "https://ytb.metvmetv83.workers.dev/?ID=UCAGVKxpAKwXMWdmcHbrvcwQ"
  }

  
]
